rvmendillo_video_to_ascii/__init__.py
rvmendillo_video_to_ascii-1.1.0.dist-info/LICENSE
rvmendillo_video_to_ascii-1.1.0.dist-info/METADATA
rvmendillo_video_to_ascii-1.1.0.dist-info/WHEEL
rvmendillo_video_to_ascii-1.1.0.dist-info/top_level.txt
rvmendillo_video_to_ascii-1.1.0.dist-info/RECORD
