Metadata-Version: 2.1
Name: rvmendillo-video-to-ascii
Version: 1.1.0
Summary: Generates and saves ASCII animation in MP4 format from a video file
Home-page: https://github.com/rvmendillo/video_to_ascii
Author: Rey Victor Mendillo
Author-email: admin@rvmendillo.com
Project-URL: Bug Tracker, https://github.com/rvmendillo/video_to_ascii/issues
Classifier: Programming Language :: Python :: 3
Classifier: License :: OSI Approved :: MIT License
Classifier: Operating System :: OS Independent
Classifier: Topic :: Multimedia :: Video :: Conversion
Classifier: Topic :: Scientific/Engineering :: Image Processing
Classifier: Topic :: Text Processing
Requires-Python: >=3.6
License-File: LICENSE
Requires-Dist: opencv-python
Requires-Dist: rvmendillo-image-to-ascii
Requires-Dist: numpy
Requires-Dist: moviepy
